pysoundcloud/__init__.py
pysoundcloud/client.py
pysoundcloud/soundclouddata.py
pysoundcloud/soundcloudlikedtracks.py
pysoundcloud/soundcloudplaylist.py
pysoundcloud/soundcloudplaylists.py
pysoundcloud/soundcloudrelatedtracks.py
pysoundcloud/soundcloudsearchresults.py
pysoundcloud/soundcloudstream.py
pysoundcloud/soundcloudstreams.py
pysoundcloud/soundcloudtrack.py
pysoundcloud/soundclouduser.py
pysoundcloud/trackdata.py
PySoundCloud-2020.6.2.dist-info/METADATA
PySoundCloud-2020.6.2.dist-info/WHEEL
PySoundCloud-2020.6.2.dist-info/license.txt
PySoundCloud-2020.6.2.dist-info/top_level.txt
PySoundCloud-2020.6.2.dist-info/RECORD
