Metadata-Version: 2.1
Name: PySoundCloud
Version: 2020.6.2
Summary: A Python wrapper for the SoundCloud API
Home-page: https://github.com/AnthonyWritesBadCode/PySoundCloud/
Author: Anthony Provenza
License: MIT License
Platform: UNKNOWN
Requires-Dist: setuptools (~=47.1.1)
Requires-Dist: requests (~=2.23.0)
Requires-Dist: urllib3 (~=1.25.9)
Requires-Dist: mutagen (~=1.44.0)
